entari_plugin_browser-0.5.0.dist-info/METADATA
entari_plugin_browser-0.5.0.dist-info/WHEEL
entari_plugin_browser-0.5.0.dist-info/entry_points.txt
entari_plugin_browser-0.5.0.dist-info/licenses/LICENSE
entari_plugin_browser/README.md
entari_plugin_browser/__init__.py
entari_plugin_browser/config.py
entari_plugin_browser/installer.py
entari_plugin_browser/service.py
entari_plugin_browser/signal.py
entari_plugin_browser/utils.py
entari_plugin_browser-0.5.0.dist-info/RECORD
