Metadata-Version: 2.1
Name: entari-plugin-browser
Version: 0.5.0
Summary: Browser API service for Entari using Playwright
Author-Email: RF-Tar-Railt <rf_tar_railt@qq.com>
License: MIT
Requires-Python: >=3.10
Requires-Dist: graiax-playwright>=0.5.0
Requires-Dist: graiax-text2img-playwright>=0.5.0
Requires-Dist: arclet-entari<0.17.0,>=0.16.1
Requires-Dist: playwright>=1.55.0
Provides-Extra: jinja
Requires-Dist: jinja2>=3.1.6; extra == "jinja"
Provides-Extra: jinja2
Requires-Dist: jinja2>=3.1.6; extra == "jinja2"
